azureml/__init__.py
azureml/contrib/__init__.py
azureml/contrib/aisc/__init__.py
azureml/contrib/aisc/_hooks.py
azureml/contrib/aisc/aisc_run.py
azureml/contrib/aisc/aiscrunconfig.py
azureml/contrib/aisc/compute/__init__.py
azureml/contrib/aisc/compute/aisupercomputer.py
azureml_contrib_aisc-1.60.0.dist-info/licenses/LICENSE.txt
azureml_contrib_aisc-1.60.0.dist-info/METADATA
azureml_contrib_aisc-1.60.0.dist-info/WHEEL
azureml_contrib_aisc-1.60.0.dist-info/entry_points.txt
azureml_contrib_aisc-1.60.0.dist-info/top_level.txt
azureml_contrib_aisc-1.60.0.dist-info/RECORD
