Metadata-Version: 2.4
Name: azureml-contrib-aisc
Version: 1.60.0
Summary: AzureML Contrib for AzureML AI Super Computer compute target.    AISC Compute is a managed AI compute infrastructure.
Home-page: https://docs.microsoft.com/python/api/overview/azure/ml/?view=azure-ml-py
Author: Microsoft Corp
License: Proprietary https://aka.ms/azureml-preview-sdk-license 
License-File: LICENSE.txt
Requires-Dist: azureml-core
Dynamic: author
Dynamic: description
Dynamic: description-content-type
Dynamic: home-page
Dynamic: license
Dynamic: license-file
Dynamic: requires-dist
Dynamic: summary
